fastobo.pypy37-pp73-aarch64-linux-gnu.so
fastobo-0.12.3.dist-info/METADATA
fastobo-0.12.3.dist-info/RECORD
fastobo-0.12.3.dist-info/COPYING
fastobo-0.12.3.dist-info/top_level.txt
fastobo-0.12.3.dist-info/WHEEL
