Metadata-Version: 2.1
Name: fastobo
Version: 0.12.3
Summary: Faultless AST for Open Biomedical Ontologies in Python.
Home-page: https://github.com/fastobo/fastobo-py
Author: Martin Larralde
Author-email: martin.larralde@embl.de
License: MIT
Project-URL: Bug Tracker, https://github.com/fastobo/fastobo-py/issues
Project-URL: Changelog, https://fastobo.readthedocs.io/en/latest/changes.html
Project-URL: Documentation, https://fastobo.readthedocs.io/en/latest/
Project-URL: Conda Recipe, https://anaconda.org/bioconda/fastobo
Keywords: ontologies,ontology,obo,obofoundry,parser,syntax,ast
Platform: any
Classifier: Development Status :: 4 - Beta
Classifier: Intended Audience :: Developers
Classifier: Intended Audience :: Science/Research
Classifier: Intended Audience :: Healthcare Industry
Classifier: License :: OSI Approved :: MIT License
Classifier: Programming Language :: Rust
Classifier: Programming Language :: Python :: 3.7
Classifier: Programming Language :: Python :: 3.8
Classifier: Programming Language :: Python :: 3.9
Classifier: Programming Language :: Python :: 3.10
Classifier: Programming Language :: Python :: 3.11
Classifier: Programming Language :: Python :: 3.12
Classifier: Programming Language :: Python :: Implementation :: CPython
Classifier: Programming Language :: Python :: Implementation :: PyPy
Classifier: Topic :: Scientific/Engineering :: Bio-Informatics
Classifier: Topic :: Scientific/Engineering :: Medical Science Apps.
Classifier: Topic :: Software Development :: Libraries :: Python Modules
Requires-Python: >=3.7
License-File: COPYING
